py_eureka_client/__aws_info_loader.py
py_eureka_client/__dns_txt_resolver.py
py_eureka_client/__init__.py
py_eureka_client/eureka_basic.py
py_eureka_client/eureka_client.py
py_eureka_client/http_client.py
py_eureka_client/logger.py
py_eureka_client/netint_utils.py
py_eureka_client-0.13.3.dist-info/licenses/LICENSE
py_eureka_client-0.13.3.dist-info/METADATA
py_eureka_client-0.13.3.dist-info/WHEEL
py_eureka_client-0.13.3.dist-info/top_level.txt
py_eureka_client-0.13.3.dist-info/RECORD
