Metadata-Version: 2.4
Name: py_eureka_client
Version: 0.13.3
Summary: A eureka client written in python. Support registering your python component to Eureka Server, as well as calling remote services by pulling the the Eureka registry. 
Author-email: keijack <keijack.wu@gmail.com>
License-Expression: MIT
Project-URL: homepage, https://github.com/keijack/python-eureka-client
Project-URL: repository, https://github.com/keijack/python-eureka-client
Keywords: eureka,netflix,microservice
Classifier: Programming Language :: Python :: 3
Classifier: Operating System :: OS Independent
Requires-Python: >=3.7
License-File: LICENSE
Requires-Dist: ifaddr>=0.2.0
Requires-Dist: dnspython>=2.4.2
Requires-Dist: httpx>=0.23.0
Dynamic: license-file
